{
  "custom": {
    "addItem": null
  },
  "params": {},
  "propConfig": {
    "custom.addItem": {
      "binding": {
        "config": {
          "fallbackDelay": 2.5,
          "mode": "indirect",
          "references": {},
          "tagPath": "[default]readQR.value"
        },
        "transforms": [
          {
            "code": "\tstore \u003d self.getChild(\"root\").getChild(\"TabContainer\").getChild(\"Add Tab\").getChild(\"QRRow\").getChild(\"Generate\").getChild(\"Name Section\").getChild(\"Name\").props.text + \"*\" + self.getChild(\"root\").getChild(\"TabContainer\").getChild(\"Add Tab\").getChild(\"QRRow\").getChild(\"Generate\").getChild(\"Quantity Section\").getChild(\"Quantity\").props.text\n\t\n\tif store \u003d\u003d \"\":\n\t\tvalue \u003d store\n\t\n\treturn value",
            "type": "script"
          }
        ],
        "type": "tag"
      },
      "persistent": true
    }
  },
  "props": {
    "defaultSize": {
      "height": 584,
      "width": 465
    }
  },
  "root": {
    "children": [
      {
        "children": [
          {
            "meta": {
              "name": "Barcode_0"
            },
            "position": {
              "grow": 1
            },
            "propConfig": {
              "props.value": {
                "binding": {
                  "config": {
                    "fallbackDelay": 2.5,
                    "mode": "direct",
                    "tagPath": "[default]readQR.value"
                  },
                  "type": "tag"
                }
              }
            },
            "props": {
              "type": "qrcode"
            },
            "type": "ia.display.barcode"
          }
        ],
        "meta": {
          "name": "QRRow"
        },
        "position": {
          "grow": 1
        },
        "props": {
          "direction": "column",
          "justify": "center",
          "style": {
            "overflow": "hidden"
          }
        },
        "type": "ia.container.flex"
      }
    ],
    "meta": {
      "name": "root"
    },
    "props": {
      "direction": "column",
      "justify": "space-evenly",
      "style": {
        "margin": "20px"
      }
    },
    "type": "ia.container.flex"
  }
}