{
  "custom": {},
  "params": {},
  "props": {
    "defaultSize": {
      "height": 221,
      "width": 768
    }
  },
  "root": {
    "children": [
      {
        "meta": {
          "name": "Asset 1"
        },
        "props": {
          "fit": {
            "height": 400,
            "mode": "contain",
            "width": 450
          },
          "source": "/system/images/Asset 1.png"
        },
        "type": "ia.display.image"
      }
    ],
    "meta": {
      "name": "root"
    },
    "props": {
      "alignItems": "center",
      "direction": "column",
      "justify": "center"
    },
    "type": "ia.container.flex"
  }
}